dcat_ms_ap/__init__.py
dcat_ms_ap/_version.py
dcat_ms_ap/datamodel/dcat_ms_ap.py
dcat_ms_ap/schema/dcat_4c_ap.yaml
dcat_ms_ap/schema/dcat_ap_plus.yaml
dcat_ms_ap/schema/dcat_ms_ap.yaml
dcat_ms_ap-0.0.2.dist-info/LICENSE
dcat_ms_ap-0.0.2.dist-info/METADATA
dcat_ms_ap-0.0.2.dist-info/WHEEL
dcat_ms_ap-0.0.2.dist-info/RECORD
