Metadata-Version: 2.3
Name: dcat_ms_ap
Version: 0.0.2
Summary: A dcat ap implementing the recommendations fo the MS MIChI.
License: CC0
Author: René Meier
Author-email: rmeier@ipb-halle.de
Requires-Python: >=3.9,<4.0
Classifier: License :: Other/Proprietary License
Classifier: Programming Language :: Python :: 3
Classifier: Programming Language :: Python :: 3.9
Classifier: Programming Language :: Python :: 3.10
Classifier: Programming Language :: Python :: 3.11
Classifier: Programming Language :: Python :: 3.12
Classifier: Programming Language :: Python :: 3.13
Requires-Dist: linkml-runtime (>=1.1.24)
